tkitDatasetEx/AutoClear.py
tkitDatasetEx/BIO.py
tkitDatasetEx/__init__.py
tkitDatasetEx/fun.py
tkitDatasetEx/readData.py
tkitDatasetEx-0.0.0.116461994.dist-info/METADATA
tkitDatasetEx-0.0.0.116461994.dist-info/WHEEL
tkitDatasetEx-0.0.0.116461994.dist-info/top_level.txt
tkitDatasetEx-0.0.0.116461994.dist-info/RECORD
